donb_tools/__init__.py
donb_tools/functions.py
donb_tools/py.typed
donb_tools/types.py
donb_tools-1.0.1.dist-info/METADATA
donb_tools-1.0.1.dist-info/WHEEL
donb_tools-1.0.1.dist-info/top_level.txt
donb_tools-1.0.1.dist-info/RECORD
