Metadata-Version: 2.1
Name: donb-tools
Version: 1.0.1
Summary: Common functions and types to reuse across personal projects
Home-page: UNKNOWN
Author: Don Beberto
Author-email: bebert64@gmail.com
License: UNKNOWN
Platform: UNKNOWN
Requires-Python: >=3.8
